cgeo/__init__.py
cgeo-0.0.3.dist-info/LICENSE.md
cgeo-0.0.3.dist-info/METADATA
cgeo-0.0.3.dist-info/WHEEL
cgeo-0.0.3.dist-info/top_level.txt
cgeo-0.0.3.dist-info/RECORD
