Metadata-Version: 2.1
Name: cgeo
Version: 0.0.3
Summary: Open source package for computational geometry
Author-email: Tom Sabala <sabala144@gmail.com>
Project-URL: Homepage, https://github.com/tomsabala/CGEO
Project-URL: Bug Tracker, https://github.com/tomsabala/CGEO/issues
Classifier: Programming Language :: Python :: 3
Classifier: License :: OSI Approved :: GNU General Public License (GPL)
Classifier: Operating System :: Unix
Requires-Python: >=3.8
License-File: LICENSE.md
